symbolic_music-0.1.0.dist-info/METADATA
symbolic_music-0.1.0.dist-info/WHEEL
symbolic_music-0.1.0.dist-info/licenses/LICENSE
symbolic_music/__init__.py
symbolic_music/_symbolic_music.pyd
symbolic_music/aria/__init__.py
symbolic_music/aria/abs_tokenizer.py
symbolic_music-0.1.0.dist-info/RECORD
