Metadata-Version: 2.4
Name: symbolic_music
Version: 0.1.0
Classifier: Programming Language :: Rust
Classifier: Programming Language :: Python :: Implementation :: CPython
Classifier: Programming Language :: Python :: Implementation :: PyPy
License-File: LICENSE
Summary: Rust library with Python bindings for symbolic music processing
Requires-Python: >=3.8
